docker_credential_chamber/__init__.py
docker_credential_chamber/cli.py
docker_credential_chamber/exception_handler.py
docker_credential_chamber/version.py
docker_credential_chamber-1.2.0.dist-info/entry_points.txt
docker_credential_chamber-1.2.0.dist-info/LICENSE
docker_credential_chamber-1.2.0.dist-info/WHEEL
docker_credential_chamber-1.2.0.dist-info/METADATA
docker_credential_chamber-1.2.0.dist-info/RECORD
