Metadata-Version: 2.1
Name: docker-credential-chamber
Version: 1.2.0
Summary: docker_credential_chamber
Keywords: docker,credential,helper,chamber
Author-email: Matt Krueger <mkrueger@rstms.net>
Requires-Python: >=3.10
Classifier: License :: OSI Approved :: MIT License
Classifier: Programming Language :: Python
Requires-Dist: click
Requires-Dist: black ; extra == "dev"
Requires-Dist: coverage ; extra == "dev"
Requires-Dist: bump2version ; extra == "dev"
Requires-Dist: isort ; extra == "dev"
Requires-Dist: flake8 ; extra == "dev"
Requires-Dist: flake8-length ; extra == "dev"
Requires-Dist: pytest ; extra == "dev"
Requires-Dist: pytest-datadir ; extra == "dev"
Requires-Dist: python-box ; extra == "dev"
Requires-Dist: tox ; extra == "dev"
Requires-Dist: pdbpp ; extra == "dev"
Requires-Dist: toml ; extra == "dev"
Requires-Dist: m2r2 ; extra == "docs"
Requires-Dist: sphinx ; extra == "docs"
Requires-Dist: sphinx-click ; extra == "docs"
Requires-Dist: sphinx-rtd-theme ; extra == "docs"
Project-URL: Home, https://github.com/rstms/docker-credential-chamber
Provides-Extra: dev
Provides-Extra: docs
